{
  "batches_completed": 75,
  "total_recordings_processed": 7000,
  "batch_history": [
    {
      "timestamp": "2026-02-27T15:24:13.234715",
      "batch_size": 100,
      "elapsed_seconds": 7.295644283294678,
      "load_before": {
        "cpu_percent": 1.125,
        "memory_percent": 24.536451651438895,
        "gpu_memory_used_mb": 3940,
        "is_underutilized": true
      }
    },
    {
      "timestamp": "2026-02-27T15:54:15.347017",
      "batch_size": 100,
      "elapsed_seconds": 7.276301860809326,
      "load_before": {
        "cpu_percent": 1.625,
        "memory_percent": 24.57996595252282,
        "gpu_memory_used_mb": 3940,
        "is_underutilized": true
      }
    },
    {
      "timestamp": "2026-02-27T16:24:13.352351",
      "batch_size": 100,
      "elapsed_seconds": 7.334024667739868,
      "load_before": {
        "cpu_percent": 0.625,
        "memory_percent": 10.43528777465893,
        "gpu_memory_used_mb": 3940,
        "is_underutilized": true
      }
    },
    {
      "timestamp": "2026-02-27T16:50:37.501689",
      "batch_size": 100,
      "elapsed_seconds": 7.345199823379517,
      "load_before": {
        "cpu_percent": 2.625,
        "memory_percent": 9.949203713836718,
        "gpu_memory_used_mb": 3740,
        "is_underutilized": true
      }
    },
    {
      "timestamp": "2026-02-27T17:20:32.851235",
      "batch_size": 100,
      "elapsed_seconds": 7.352509260177612,
      "load_before": {
        "cpu_percent": 5.625,
        "memory_percent": 10.273863950718987,
        "gpu_memory_used_mb": 3976,
        "is_underutilized": true
      }
    },
    {
      "timestamp": "2026-02-27T17:50:32.575695",
      "batch_size": 100,
      "elapsed_seconds": 7.319765090942383,
      "load_before": {
        "cpu_percent": 1.25,
        "memory_percent": 10.499275815950925,
        "gpu_memory_used_mb": 7416,
        "is_underutilized": true
      }
    },
    {
      "timestamp": "2026-02-27T18:08:00.076903",
      "batch_size": 100,
      "elapsed_seconds": 7.214585542678833,
      "load_before": {
        "cpu_percent": 26.625,
        "memory_percent": 17.47464747576909,
        "gpu_memory_used_mb": 3740,
        "is_underutilized": true
      }
    },
    {
      "timestamp": "2026-02-27T18:08:18.582003",
      "batch_size": 100,
      "elapsed_seconds": 7.181169748306274,
      "load_before": {
        "cpu_percent": 19.75,
        "memory_percent": 18.29587194411484,
        "gpu_memory_used_mb": 3740,
        "is_underutilized": true
      }
    },
    {
      "timestamp": "2026-02-27T18:23:22.920403",
      "batch_size": 100,
      "elapsed_seconds": 7.198202610015869,
      "load_before": {
        "cpu_percent": 22.125,
        "memory_percent": 25.896191446380335,
        "gpu_memory_used_mb": 3740,
        "is_underutilized": true
      }
    },
    {
      "timestamp": "2026-02-27T18:23:41.314440",
      "batch_size": 100,
      "elapsed_seconds": 7.103728294372559,
      "load_before": {
        "cpu_percent": 28.000000000000004,
        "memory_percent": 26.793167536993234,
        "gpu_memory_used_mb": 3740,
        "is_underutilized": true
      }
    },
    {
      "timestamp": "2026-02-27T18:24:02.761912",
      "batch_size": 100,
      "elapsed_seconds": 7.162044525146484,
      "load_before": {
        "cpu_percent": 21.625,
        "memory_percent": 26.865963057733033,
        "gpu_memory_used_mb": 3740,
        "is_underutilized": true
      }
    },
    {
      "timestamp": "2026-02-27T18:36:58.761399",
      "batch_size": 100,
      "elapsed_seconds": 7.183646202087402,
      "load_before": {
        "cpu_percent": 8.125,
        "memory_percent": 26.321207072357332,
        "gpu_memory_used_mb": 3740,
        "is_underutilized": true
      }
    },
    {
      "timestamp": "2026-02-27T19:06:58.067677",
      "batch_size": 100,
      "elapsed_seconds": 7.246457099914551,
      "load_before": {
        "cpu_percent": 0.8750000000000001,
        "memory_percent": 25.863540514283812,
        "gpu_memory_used_mb": 3740,
        "is_underutilized": true
      }
    },
    {
      "timestamp": "2026-02-28T09:01:46.018423",
      "batch_size": 100,
      "elapsed_seconds": 7.2754926681518555,
      "load_before": {
        "cpu_percent": 28.125,
        "memory_percent": 29.598163764271078,
        "gpu_memory_used_mb": 3634,
        "is_underutilized": true
      }
    },
    {
      "timestamp": "2026-02-28T09:31:28.528791",
      "batch_size": 100,
      "elapsed_seconds": 7.255573749542236,
      "load_before": {
        "cpu_percent": 26.375,
        "memory_percent": 27.937461660185082,
        "gpu_memory_used_mb": 3634,
        "is_underutilized": true
      }
    },
    {
      "timestamp": "2026-02-28T10:01:19.622641",
      "batch_size": 100,
      "elapsed_seconds": 7.608518362045288,
      "load_before": {
        "cpu_percent": 21.625,
        "memory_percent": 20.53205094477516,
        "gpu_memory_used_mb": 3634,
        "is_underutilized": true
      }
    },
    {
      "timestamp": "2026-02-28T10:31:19.253303",
      "batch_size": 100,
      "elapsed_seconds": 7.600465774536133,
      "load_before": {
        "cpu_percent": 15.625,
        "memory_percent": 19.953996784093587,
        "gpu_memory_used_mb": 3634,
        "is_underutilized": true
      }
    },
    {
      "timestamp": "2026-02-28T11:01:18.994406",
      "batch_size": 100,
      "elapsed_seconds": 7.528447389602661,
      "load_before": {
        "cpu_percent": 15.25,
        "memory_percent": 8.602899425218313,
        "gpu_memory_used_mb": 3634,
        "is_underutilized": true
      }
    },
    {
      "timestamp": "2026-02-28T11:31:18.939856",
      "batch_size": 100,
      "elapsed_seconds": 7.499119758605957,
      "load_before": {
        "cpu_percent": 15.5,
        "memory_percent": 9.076410775932464,
        "gpu_memory_used_mb": 3634,
        "is_underutilized": true
      }
    },
    {
      "timestamp": "2026-02-28T12:01:19.236960",
      "batch_size": 100,
      "elapsed_seconds": 7.4738311767578125,
      "load_before": {
        "cpu_percent": 15.75,
        "memory_percent": 9.051842881043392,
        "gpu_memory_used_mb": 3634,
        "is_underutilized": true
      }
    }
  ],
  "average_batch_time_seconds": 7.322736394405365,
  "last_check": "2026-02-28T12:01:11.725332"
}